discordland/__init__.py
discordland/client.py
discordland/errors.py
discordland/results.py
discordland.py-0.0.1.dist-info/LICENSE
discordland.py-0.0.1.dist-info/METADATA
discordland.py-0.0.1.dist-info/WHEEL
discordland.py-0.0.1.dist-info/top_level.txt
discordland.py-0.0.1.dist-info/RECORD
